README.md
setup.py
bin/check_mypy_annotations.py
bin/mypy_server.py
bin/print_mypy_coverage.py
mypytools/__init__.py
mypytools/config.py
mypytools/source_utils.py
mypytools.egg-info/PKG-INFO
mypytools.egg-info/SOURCES.txt
mypytools.egg-info/dependency_links.txt
mypytools.egg-info/not-zip-safe
mypytools.egg-info/pbr.json
mypytools.egg-info/requires.txt
mypytools.egg-info/top_level.txt
mypytools/server/__init__.py
mypytools/server/mypy_event_handler.py
mypytools/server/mypy_file_cache.py
mypytools/server/mypy_http_request_handler.py
mypytools/server/mypy_queueing_handler.py
mypytools/server/mypy_server.py
mypytools/server/mypy_task.py
mypytools/server/mypy_worker.py