Metadata-Version: 1.0
Name: mypytools
Version: 0.1.11
Summary: A bundle of tools to make using mypy easier
Home-page: https://github.com/nylas/mypy-tools
Author: UNKNOWN
Author-email: UNKNOWN
License: MIT
Platform: UNKNOWN
